mymailsender/__init__.py
mymailsender/my_mail_sender.py
tests/test_mailsender.py
mymailsender-0.1.6.dist-info/METADATA
mymailsender-0.1.6.dist-info/WHEEL
mymailsender-0.1.6.dist-info/top_level.txt
mymailsender-0.1.6.dist-info/RECORD
