Metadata-Version: 2.1
Name: mymailsender
Version: 0.1.6
Summary: A simple Python mailer for SMTP sending.
Author-email: Marius Berge Eide <mariusbe@gmail.com>
License: MIT
Project-URL: Source Code, https://github.com/mariusei/mymailsender
Keywords: smtp,email,mailer
Classifier: Programming Language :: Python :: 3
Classifier: Operating System :: OS Independent
